milkman_py/__init__.py
milkman_py/main.py
milkman_py-0.1.1.dist-info/WHEEL
milkman_py-0.1.1.dist-info/METADATA
milkman_py-0.1.1.dist-info/RECORD
